{
    "category": "MapView",
    "description": "Rotate a map.",
    "ignore": false,
    "images": "MapRotation.jpg",
    "keywords": [
        "SetViewpointRotationAsync",
        "rotate"
    ],
    "offline_data": [],
    "redirect_from": [
        "/net/latest/wpf/sample-code/maprotation.htm"
    ],
    "relevant_apis": [
        "Compass",
        "Map",
        "MapView"
    ],
    "sample_unique_id": "",
    "snippets": [
        "MapRotation.xaml",
        "MapRotation.xaml.cs"
    ],
    "title": "Map rotation"
}