{
    "category": "MapView",
    "description": "Determine if a layer is currently being viewed.",
    "formal_name": "DisplayLayerViewState",
    "ignore": false,
    "images": [
        "DisplayLayerViewState.jpg"
    ],
    "keywords": [
        "layer",
        "load",
        "map",
        "status",
        "view",
        "visibility"
    ],
    "offline_data": [],
    "redirect_from": [
        "/net/latest/wpf/sample-code/display-layer-view-state.htm"
    ],
    "relevant_apis": [
        "LayerViewStateChanged",
        "LayerViewStateChangedEventArgs",
        "Map",
        "MapView"
    ],
    "snippets": [
        "DisplayLayerViewState.xaml.cs",
        "DisplayLayerViewState.xaml"
    ],
    "title": "Display layer view state"
}