{
    "category": "Layers",
    "description": "Select features in a feature layer.",
    "ignore": false,
    "images": "FeatureLayerSelection.jpg",
    "keywords": [
        "Layers",
        "SelectFeaturesAsync",
        "SelectionMode",
        "select",
        "tolerance"
    ],
    "offline_data": [],
    "redirect_from": [
        "/net/latest/android/sample-code/featurelayerselection.htm"
    ],
    "relevant_apis": [
        "Feature",
        "FeatureLayer",
        "ServiceFeatureTable"
    ],
    "snippets": [
        "FeatureLayerSelection.cs"
    ],
    "title": "Feature layer selection"
}