{
    "category": "Layers",
    "description": "Display an OGC API feature collection and query features while navigating the map view.",
    "formal_name": "DisplayOACollection",
    "ignore": false,
    "images": [
        "DisplayOACollection.jpg"
    ],
    "keywords": [
        "OGC",
        "OGC API",
        "feature",
        "feature layer",
        "feature table",
        "service",
        "table",
        "web"
    ],
    "nuget_packages": {
        "Esri.ArcGISRuntime": "100.11.2",
        "Esri.ArcGISRuntime.Xamarin.iOS": "100.11.2"
    },
    "offline_data": [],
    "redirect_from": [
        "/net/latest/ios/sample-code/displayoacollection.htm"
    ],
    "relevant_apis": [
        "OgcFeatureCollectionTable",
        "QueryParameters"
    ],
    "snippets": [
        "DisplayOACollection.cs"
    ],
    "title": "Display OGC API collection"
}