{
    "category": "Layers",
    "description": "Add an ArcGIS Map Image Layer from a URL to a map.",
    "formal_name": "ArcGISMapImageLayerUrl",
    "ignore": false,
    "images": [
        "ArcGISMapImageLayerUrl.jpg"
    ],
    "keywords": [
        "ArcGIS dynamic map service layer",
        "ArcGISMapImageLayer",
        "layers"
    ],
    "nuget_packages": {
        "Esri.ArcGISRuntime": "100.5.0"
    },
    "offline_data": [],
    "redirect_from": [
        "/net/latest/ios/sample-code/arcgismapimagelayerurl.htm"
    ],
    "relevant_apis": [
        "ArcGISMapImageLayer",
        "Map",
        "MapView"
    ],
    "snippets": [
        "ArcGISMapImageLayerUrl.cs"
    ],
    "title": "ArcGIS map image layer"
}